[
  {
    "user": "হ্যালো, আপনি কি আজ লখনউয়ের আবহাওয়ার সম্পর্কে বলতে পারেন?",
    "bot": "অবশ্যই! এখন লখনউয়ে রোদ ঝলমলে আবহাওয়া, এবং সর্বোচ্চ তাপমাত্রা ৩৫ ডিগ্রি সেলসিয়াস। আপনি আর কিছুর সাহায্য চান কি?"
  },
  {
    "user": "শহরের কিছু জনপ্রিয় পর্যটনস্থল কী কী?",
    "bot": "লখনউ বহু ঐতিহাসিক স্থানের জন্য বিখ্যাত, যেমন বড় ইমামবাড়া, ছোট ইমামবাড়া এবং রুমি দরওয়াজা। অনেক পর্যটক হজরতগঞ্জ মার্কেটে হাঁটতে পছন্দ করেন।"
  },
  {
    "user": "শহরের কিছু জনপ্রিয় পর্যটনস্থল কী কী?",
    "bot": "লখনউ বহু ঐতিহাসিক স্থানের জন্য বিখ্যাত, যেমন বড় ইমামবাড়া, ছোট ইমামবাড়া এবং রুমি দরওয়াজা। অনেক পর্যটক হজরতগঞ্জ মার্কেটে হাঁটতে পছন্দ করেন।"
  },
  {
    "user": "আপনি কি আমার জন্য একটি ফ্লাইট বুক করতে পারেন? আমার ইমেল test@example.com",
    "bot": "আমি সরাসরি বুকিং করতে পারি না। অনুগ্রহ করে একটি ট্রাভেল এজেন্টের সাথে যোগাযোগ করুন। আপনার ইমেল test@example.com।"
  },
  {
    "user": "হাই",
    "bot": "ঠিক আছে।"
  }
]
